README.md
setup.cfg
setup.py
./pydbm/__init__.py
./pydbm/params_initializer.c
./pydbm/params_initializer.pyx
./pydbm/synapse_list.c
./pydbm/synapse_list.pyx
./pydbm/activation/__init__.py
./pydbm/activation/identity_function.c
./pydbm/activation/identity_function.pyx
./pydbm/activation/logistic_function.c
./pydbm/activation/logistic_function.pyx
./pydbm/activation/relu_function.c
./pydbm/activation/relu_function.pyx
./pydbm/activation/sign_function.c
./pydbm/activation/sign_function.pyx
./pydbm/activation/softmax_function.c
./pydbm/activation/softmax_function.pyx
./pydbm/activation/tanh_function.c
./pydbm/activation/tanh_function.pyx
./pydbm/activation/interface/__init__.py
./pydbm/activation/interface/activating_function_interface.c
./pydbm/activation/interface/activating_function_interface.pyx
./pydbm/activation/signfunction/__init__.py
./pydbm/activation/signfunction/deterministic_binary_neurons.c
./pydbm/activation/signfunction/deterministic_binary_neurons.pyx
./pydbm/activation/signfunction/stochastic_binary_neurons.c
./pydbm/activation/signfunction/stochastic_binary_neurons.pyx
./pydbm/activation/softmaxfunction/__init__.py
./pydbm/activation/softmaxfunction/log_softmax_function.c
./pydbm/activation/softmaxfunction/log_softmax_function.pyx
./pydbm/approximation/__init__.py
./pydbm/approximation/contrastive_divergence.c
./pydbm/approximation/contrastive_divergence.pyx
./pydbm/approximation/rt_rbm_cd.c
./pydbm/approximation/rt_rbm_cd.pyx
./pydbm/approximation/shape_bm_cd.c
./pydbm/approximation/shape_bm_cd.pyx
./pydbm/approximation/interface/__init__.py
./pydbm/approximation/interface/approximate_interface.c
./pydbm/approximation/interface/approximate_interface.pyx
./pydbm/approximation/rtrbmcd/__init__.py
./pydbm/approximation/rtrbmcd/lstm_rt_rbm_cd.c
./pydbm/approximation/rtrbmcd/lstm_rt_rbm_cd.pyx
./pydbm/approximation/rtrbmcd/rnn_rbm_cd.c
./pydbm/approximation/rtrbmcd/rnn_rbm_cd.pyx
./pydbm/clustering/__init__.py
pydbm.egg-info/PKG-INFO
pydbm.egg-info/SOURCES.txt
pydbm.egg-info/dependency_links.txt
pydbm.egg-info/requires.txt
pydbm.egg-info/top_level.txt
