Metadata-Version: 2.1
Name: pydbm
Version: 1.5.1
Summary: `pydbm` is Python library for building Restricted Boltzmann Machine(RBM), Deep Boltzmann Machine(DBM), Long Short-Term Memory Recurrent Temporal Restricted Boltzmann Machine(LSTM-RTRBM), and Shape Boltzmann Machine(Shape-BM). From the view points of functionally equivalents and structural expansions, this library also prototypes many variants such as Encoder/Decoder based on LSTM, Convolutional Auto-Encoder, and Spatio-temporal Auto-Encoder.
Home-page: https://github.com/chimera0/accel-brain-code/tree/master/Deep-Learning-by-means-of-Design-Pattern
Author: chimera0
Author-email: ai-brain-lab@accel-brain.com
License: GPL2
Keywords: restricted boltzmann machine autoencoder auto-encoder rnn rbm rtrbm convolution deconvolution spatio-temporal encoder decoder LSTM
Platform: UNKNOWN
Classifier: Development Status :: 5 - Production/Stable
Classifier: Intended Audience :: Information Technology
Classifier: Intended Audience :: Science/Research
Classifier: Topic :: Text Processing
Classifier: Topic :: Scientific/Engineering :: Artificial Intelligence
Classifier: License :: OSI Approved :: GNU General Public License v2 (GPLv2)
Classifier: Programming Language :: Python :: 3
